eazyctrl.py
eazyctrl-0.4.dist-info/LICENSE.txt
eazyctrl-0.4.dist-info/METADATA
eazyctrl-0.4.dist-info/WHEEL
eazyctrl-0.4.dist-info/entry_points.txt
eazyctrl-0.4.dist-info/top_level.txt
eazyctrl-0.4.dist-info/RECORD
