Metadata-Version: 2.1
Name: eazyctrl
Version: 0.4
Summary: Monitoring and controlling Easy Controls KWL (air exchanger)devices via Modbus/TCP.
Home-page: https://github.com/baradi09/eazyctrl
Author: Bálint Aradi
Author-email: baradi09@gmail.com
License: BSD
Keywords: easycontrols kwl air-exchanger
Platform: UNKNOWN
Classifier: Development Status :: 4 - Beta
Classifier: License :: OSI Approved :: BSD License
Classifier: Programming Language :: Python :: 3
Classifier: Topic :: Home Automation
License-File: LICENSE.txt
